aurpkg/main.py
aurpkg-0.1.1.dist-info/LICENSE
aurpkg-0.1.1.dist-info/METADATA
aurpkg-0.1.1.dist-info/WHEEL
aurpkg-0.1.1.dist-info/entry_points.txt
aurpkg-0.1.1.dist-info/RECORD
