Metadata-Version: 2.1
Name: aurpkg
Version: 0.1.1
Summary: aurumOS Package Manager
Author: lxchn1v1
Author-email: flat.assembly@gmail.com
Requires-Python: >=3.10,<4.0
Classifier: Programming Language :: Python :: 3
Classifier: Programming Language :: Python :: 3.10
Classifier: Programming Language :: Python :: 3.11
Requires-Dist: aurum-os-base
Requires-Dist: pip
Requires-Dist: requests
